odoo/addons/test_component/README.rst
odoo/addons/test_component/__init__.py
odoo/addons/test_component/__manifest__.py
odoo/addons/test_component/components/__init__.py
odoo/addons/test_component/components/components.py
odoo/addons/test_component/i18n/am.po
odoo/addons/test_component/i18n/ca.po
odoo/addons/test_component/i18n/de.po
odoo/addons/test_component/i18n/el_GR.po
odoo/addons/test_component/i18n/es.po
odoo/addons/test_component/i18n/es_ES.po
odoo/addons/test_component/i18n/fi.po
odoo/addons/test_component/i18n/fr.po
odoo/addons/test_component/i18n/gl.po
odoo/addons/test_component/i18n/it.po
odoo/addons/test_component/i18n/pt.po
odoo/addons/test_component/i18n/pt_BR.po
odoo/addons/test_component/i18n/pt_PT.po
odoo/addons/test_component/i18n/sl.po
odoo/addons/test_component/i18n/test_component.pot
odoo/addons/test_component/i18n/tr.po
odoo/addons/test_component/i18n/zh_CN.po
odoo/addons/test_component/models/__init__.py
odoo/addons/test_component/models/models.py
odoo/addons/test_component/readme/CONTRIBUTORS.rst
odoo/addons/test_component/readme/DESCRIPTION.rst
odoo/addons/test_component/security/ir.model.access.csv
odoo/addons/test_component/static/description/icon.png
odoo/addons/test_component/static/description/index.html
odoo/addons/test_component/tests/__init__.py
odoo/addons/test_component/tests/test_component_collection.py
odoo/addons/test_component/tests/test_components.py
odoo14_addon_test_component-14.0.1.0.1.dev9.dist-info/METADATA
odoo14_addon_test_component-14.0.1.0.1.dev9.dist-info/WHEEL
odoo14_addon_test_component-14.0.1.0.1.dev9.dist-info/top_level.txt
odoo14_addon_test_component-14.0.1.0.1.dev9.dist-info/RECORD
