Metadata-Version: 2.1
Name: odoo14-addon-test_component
Version: 14.0.1.0.1.dev9
Summary: Automated tests for Components, do not install.
Home-page: https://github.com/OCA/connector
Author: Camptocamp,Odoo Community Association (OCA)
Author-email: support@odoo-community.org
License: LGPL-3
Classifier: Programming Language :: Python
Classifier: Framework :: Odoo
Classifier: Framework :: Odoo :: 14.0
Classifier: License :: OSI Approved :: GNU Lesser General Public License v3 (LGPLv3)
Classifier: Development Status :: 5 - Production/Stable
Requires-Python: >=3.6
Requires-Dist: odoo14-addon-component
Requires-Dist: odoo<14.1dev,>=14.0a
